speechai/__init__.py
speechai/core/__init__.py
speechai/core/speechai.py
speechai/llm/__init__.py
speechai/llm/abstract_llm.py
speechai/llm/cohere.py
speechai/llm/openai.py
speechai/tts/__init__.py
speechai/tts/abstract_tts.py
speechai/tts/gtts.py
speechai/utils/__init__.py
speechai/utils/directory.py
speechai/utils/logger.py
speechai-0.0.3.dist-info/LICENSE
speechai-0.0.3.dist-info/METADATA
speechai-0.0.3.dist-info/WHEEL
speechai-0.0.3.dist-info/RECORD
