Metadata-Version: 2.1
Name: speechai
Version: 0.0.3
Summary: A Python package that generates conversational speech from text using a combination of Generative AI models and various text-to-speech engines, enabling applications to produce dynamic and contextually aware spoken responses.
License: Apache-2.0
Author: Nicola Sebastianelli
Requires-Python: >=3.8.1,<4.0.0
Classifier: License :: OSI Approved :: Apache Software License
Classifier: Programming Language :: Python :: 3
Classifier: Programming Language :: Python :: 3.9
Classifier: Programming Language :: Python :: 3.10
Classifier: Programming Language :: Python :: 3.11
Requires-Dist: cohere (>=4.5.1,<5.0.0)
Requires-Dist: gtts (>=2.3.2,<3.0.0)
Requires-Dist: openai (>=0.27.7,<0.28.0)
Requires-Dist: python-dotenv (>=1.0.0,<2.0.0)
